{
    "NUM_HighPtMuons": {
        "abseta_p": {
            "abseta:[0.0,1.6]": {
                "p:[100,150]": {
                    "value": 0.9948
                },
                "p:[150,200]": {
                    "value": 0.9950
                },
                "p:[200,300]": {
                    "value": 0.994
                },
                "p:[300,400]": {
                    "value": 0.9914
                },
                "p:[400,600]": {
                    "value": 0.993
                },
                "p:[600,1500]": {
                    "value": 0.991
                },
                "p:[1500,3500]": {
                    "value": 1.0
                }
            },
            "abseta:[1.6,2.4]": {
                "p:[100,150]": {
                    "value": 0.993
                },
                "p:[150,200]": {
                    "value": 0.990
                },
                "p:[200,300]": {
                    "value": 0.988
                },
                "p:[300,400]": {
                    "value": 0.981
                },
                "p:[400,600]": {
                    "value": 0.983
                },
                "p:[600,1500]": {
                    "value": 0.978
                },
                "p:[1500,3500]": {
                    "value": 0.98
                }
            }
        }
    }
}
